{"page1": {"panel1": {"id": 1, "panel_shape": {"polygon": {"coords": [[66, 28], [598, 25], [598, 489], [65, 491], [66, 26], [66, 26]]}, "bounding_box": {"coords": [[64, 26], [64, 489], [597, 489], [597, 26], [64, 26]], "pascal_voc_coords": [26, 64, 489, 597]}}, "agents": {"agent1": {"id": 1, "agent_shape": {"polygon": {"coords": [[102, 261], [123, 252], [146, 249], [148, 240], [156, 239], [160, 243], [160, 254], [155, 258], [149, 256], [118, 269], [123, 292], [126, 292], [126, 282], [134, 271], [146, 270], [153, 276], [156, 284], [157, 287], [153, 294], [144, 299], [146, 305], [156, 310], [158, 318], [166, 328], [164, 315], [159, 300], [162, 297], [167, 303], [171, 291], [172, 288], [180, 295], [179, 303], [174, 312], [177, 326], [178, 347], [173, 354], [164, 350], [157, 341], [149, 331], [143, 328], [137, 330], [128, 340], [128, 345], [144, 356], [162, 369], [168, 375], [164, 381], [153, 408], [137, 409], [141, 398], [148, 382], [148, 380], [132, 371], [122, 366], [112, 364], [109, 377], [109, 390], [111, 398], [105, 405], [98, 408], [84, 423], [79, 426], [72, 424], [76, 409], [85, 397], [90, 389], [87, 372], [86, 356], [90, 340], [97, 322], [103, 302], [103, 292], [102, 283], [102, 274]]}}, "referent": "X1", "introduced_coreferent": "none", "animacy_type": "human"}, "agent2": {"id": 2, "agent_shape": {"polygon": {"coords": [[274, 277], [284, 268], [294, 261], [290, 242], [281, 224], [271, 221], [262, 219], [257, 222], [256, 224], [257, 231], [257, 239], [253, 242], [246, 248], [245, 255], [243, 267], [233, 271], [226, 271], [217, 271], [217, 264], [221, 264], [222, 252], [216, 244], [211, 241], [207, 234], [213, 224], [210, 220], [212, 217], [219, 208], [225, 203], [228, 196], [228, 190], [224, 177], [233, 183], [235, 197], [246, 191], [259, 187], [262, 179], [270, 184], [299, 178], [350, 173], [398, 174], [430, 177], [472, 187], [430, 181], [385, 184], [350, 192], [338, 198], [332, 202], [334, 206], [347, 219], [352, 229], [362, 231], [380, 222], [401, 216], [414, 216], [424, 217], [438, 214], [461, 210], [484, 212], [502, 216], [522, 221], [545, 237], [564, 258], [574, 285], [577, 301], [577, 314], [580, 321], [591, 328], [596, 338], [598, 433], [589, 413], [588, 374], [584, 373], [582, 405], [575, 424], [560, 447], [541, 463], [511, 476], [474, 479], [438, 478], [402, 474], [380, 470], [354, 470], [326, 473], [301, 478], [287, 482], [276, 488], [261, 489], [269, 476], [293, 462], [318, 452], [351, 447], [383, 447], [420, 448], [456, 447], [488, 440], [506, 431], [518, 420], [523, 407], [522, 385], [520, 369], [508, 349], [502, 335], [496, 330], [486, 313], [482, 316], [491, 326], [483, 343], [488, 351], [490, 367], [490, 377], [485, 375], [484, 358], [480, 359], [481, 373], [478, 382], [452, 387], [439, 401], [432, 413], [429, 424], [412, 432], [396, 429], [378, 430], [360, 421], [377, 413], [403, 395], [419, 374], [428, 359], [430, 351], [424, 344], [423, 339], [412, 335], [410, 348], [410, 354], [400, 353], [386, 348], [384, 346], [387, 334], [382, 324], [382, 324], [375, 358], [368, 385], [358, 391], [324, 399], [321, 394], [335, 378], [344, 354], [341, 329], [334, 337], [325, 338], [317, 371], [302, 380], [290, 379], [285, 374], [294, 362], [296, 338], [295, 326], [291, 323], [285, 311], [277, 309], [269, 298], [271, 286]]}}, "referent": "X2", "introduced_coreferent": "none", "animacy_type": "animallike"}}, "text_sections": {"text_section1": {"id": 1, "text_section_shape": {"bounding_box": {"coords": [[66, 27], [66, 70], [587, 70], [587, 27], [66, 27]], "pascal_voc_coords": [27, 66, 70, 587]}}, "speaker_referent": "N/A", "type": "subtitle", "text": "You're fourteen, and this is the year 2095... Men probe the stars... Up there, a million strange worlds beckon... until you can stand it no longer... Until you set out on a ..."}, "text_section2": {"id": 2, "text_section_shape": {"bounding_box": {"coords": [[82, 71], [82, 230], [523, 230], [523, 71], [82, 71]], "pascal_voc_coords": [71, 82, 230, 523]}}, "speaker_referent": "N/A", "type": "title", "text": "Forbidden Journey!"}}, "setting": {"location_referent": "L1", "location_information_amount_ordinal": 5, "location_information_amount_binary": 1}}, "panel2": {"id": 2, "panel_shape": {"polygon": {"coords": [[64, 499], [320, 499], [320, 717], [63, 716], [64, 499], [64, 499]]}, "bounding_box": {"coords": [[64, 499], [64, 716], [319, 716], [319, 499], [64, 499]], "pascal_voc_coords": [499, 64, 716, 319]}}, "agents": {"agent1": {"id": 1, "agent_shape": {"polygon": {"coords": [[113, 611], [127, 602], [128, 597], [128, 590], [133, 585], [147, 588], [148, 595], [144, 607], [142, 607], [145, 612], [144, 651], [145, 673], [145, 688], [137, 697], [146, 703], [144, 705], [131, 704], [130, 700], [134, 685], [125, 701], [121, 706], [126, 712], [126, 715], [113, 714], [114, 700], [122, 675], [120, 658], [124, 644], [118, 629], [100, 648], [96, 655], [88, 655], [85, 646], [98, 640], [110, 622]]}}, "referent": "X3", "introduced_coreferent": "none", "animacy_type": "human"}, "agent2": {"id": 2, "agent_shape": {"polygon": {"coords": [[250, 593], [262, 594], [262, 608], [270, 611], [266, 637], [267, 679], [263, 684], [260, 680], [257, 650], [250, 677], [249, 684], [243, 683], [242, 675], [247, 644], [243, 639], [243, 612], [253, 608], [249, 605]]}}, "referent": "X1", "introduced_coreferent": "none", "animacy_type": "human"}}, "text_sections": {"text_section1": {"id": 1, "text_section_shape": {"bounding_box": {"coords": [[66, 501], [66, 539], [318, 539], [318, 501], [66, 501]], "pascal_voc_coords": [501, 66, 539, 318]}}, "speaker_referent": "N/A", "type": "third_person_narration", "text": "This yearning inside you -- it's like an ache, you look up -- up -- and when you see the trails of fire, your heart follows them..."}, "text_section2": {"id": 2, "text_section_shape": {"bounding_box": {"coords": [[66, 541], [66, 584], [187, 584], [187, 541], [66, 541]], "pascal_voc_coords": [541, 66, 584, 187]}}, "speaker_referent": "X3", "type": "speech", "text": "Dreaming again, Joey? I thought you'd be asleep by now!"}, "text_section3": {"id": 3, "text_section_shape": {"bounding_box": {"coords": [[233, 542], [233, 582], [317, 582], [317, 542], [233, 542]], "pascal_voc_coords": [542, 233, 582, 317]}}, "speaker_referent": "X1", "type": "speech", "text": "I-I'm just watching the rockets, Dad!"}}, "setting": {"location_referent": "L2", "location_information_amount_ordinal": 5, "location_information_amount_binary": 1}}, "panel3": {"id": 3, "panel_shape": {"polygon": {"coords": [[330, 499], [599, 497], [601, 718], [329, 717], [330, 499], [330, 499]]}, "bounding_box": {"coords": [[328, 498], [328, 716], [597, 716], [597, 498], [328, 498]], "pascal_voc_coords": [498, 328, 716, 597]}}, "agents": {"agent1": {"id": 1, "agent_shape": {"polygon": {"coords": [[343, 592], [358, 583], [353, 569], [352, 548], [353, 537], [364, 526], [392, 524], [402, 539], [400, 552], [396, 576], [393, 582], [395, 590], [414, 599], [440, 608], [446, 622], [448, 645], [453, 664], [431, 670], [425, 675], [420, 699], [410, 698], [408, 702], [411, 716], [334, 715], [335, 695], [332, 695], [331, 599]]}}, "referent": "X3", "introduced_coreferent": "none", "animacy_type": "human"}, "agent2": {"id": 2, "agent_shape": {"polygon": {"coords": [[493, 588], [513, 591], [525, 598], [531, 608], [530, 624], [529, 625], [521, 648], [517, 648], [503, 662], [518, 675], [535, 683], [539, 690], [537, 706], [538, 716], [413, 715], [420, 697], [426, 677], [433, 669], [457, 664], [474, 653], [475, 645], [472, 640], [469, 624], [469, 610], [471, 602], [481, 593]]}}, "referent": "X1", "introduced_coreferent": "none", "animacy_type": "human"}}, "text_sections": {"text_section1": {"id": 1, "text_section_shape": {"bounding_box": {"coords": [[331, 500], [331, 553], [471, 553], [471, 500], [331, 500]], "pascal_voc_coords": [500, 331, 553, 471]}}, "speaker_referent": "X3", "type": "speech", "text": "Watching -- and wishing you were on board one of them, Joey!"}, "text_section2": {"id": 2, "text_section_shape": {"bounding_box": {"coords": [[450, 501], [450, 582], [595, 582], [595, 501], [450, 501]], "pascal_voc_coords": [501, 450, 582, 595]}}, "speaker_referent": "X1", "type": "speech", "text": "Yes, Dad -- it's so dull here! Nothing ever happens! If I could only be there -- if I could only be going somewhere... anywhere!!!"}}, "setting": {"location_referent": "L2", "location_information_amount_ordinal": 3, "location_information_amount_binary": 1}}}, "page2": {"panel1": {"id": 1, "panel_shape": {"polygon": {"coords": [[54, 18], [313, 21], [313, 246], [49, 245], [53, 16], [53, 16]]}, "bounding_box": {"coords": [[52, 18], [52, 245], [311, 245], [311, 18], [52, 18]], "pascal_voc_coords": [18, 52, 245, 311]}}, "agents": {}, "text_sections": {"text_section1": {"id": 1, "text_section_shape": {"bounding_box": {"coords": [[55, 19], [55, 118], [163, 118], [163, 19], [55, 19]], "pascal_voc_coords": [19, 55, 118, 163]}}, "speaker_referent": "X3", "type": "speech", "text": "I know, Joey! It must be dull for you! But I'm a prospector. Someday, maybe, I'll make a strike! Then you'll have your chance --"}}, "setting": {"location_referent": "L3", "location_information_amount_ordinal": 5, "location_information_amount_binary": 1}}, "panel2": {"id": 2, "panel_shape": {"polygon": {"coords": [[326, 21], [610, 22], [605, 252], [322, 247], [324, 20], [324, 20]]}, "bounding_box": {"coords": [[324, 20], [324, 248], [607, 248], [607, 20], [324, 20]], "pascal_voc_coords": [20, 324, 248, 607]}}, "agents": {"agent1": {"id": 1, "agent_shape": {"polygon": {"coords": [[363, 115], [382, 97], [386, 79], [391, 72], [414, 71], [424, 80], [422, 93], [412, 110], [400, 109], [400, 113], [403, 120], [410, 135], [427, 129], [416, 139], [427, 149], [461, 151], [464, 144], [463, 138], [474, 146], [474, 160], [465, 162], [457, 163], [415, 169], [401, 160], [398, 175], [416, 184], [430, 195], [433, 204], [415, 211], [402, 211], [402, 214], [405, 235], [405, 246], [380, 246], [373, 229], [370, 247], [347, 246], [352, 218], [378, 216], [402, 212], [419, 209], [431, 203], [432, 199], [423, 191], [410, 182], [397, 175], [375, 166], [358, 159], [360, 143], [360, 126]]}}, "referent": "X3", "introduced_coreferent": "none", "animacy_type": "human"}, "agent2": {"id": 2, "agent_shape": {"polygon": {"coords": [[440, 92], [455, 98], [463, 104], [455, 128], [449, 128], [447, 133], [462, 138], [466, 138], [476, 147], [474, 162], [465, 164], [467, 182], [466, 221], [469, 232], [460, 245], [454, 238], [450, 247], [422, 246], [421, 224], [418, 225], [417, 227], [413, 220], [414, 212], [433, 204], [431, 197], [411, 183], [412, 168], [416, 171], [466, 162], [475, 162], [476, 148], [463, 140], [461, 152], [429, 151], [418, 139], [423, 130], [436, 125], [434, 122], [429, 119], [432, 109], [431, 102]]}}, "referent": "X1", "introduced_coreferent": "none", "animacy_type": "human"}}, "text_sections": {"text_section1": {"id": 1, "text_section_shape": {"bounding_box": {"coords": [[326, 21], [326, 71], [474, 71], [474, 21], [326, 21]], "pascal_voc_coords": [21, 326, 71, 474]}}, "speaker_referent": "X3", "type": "speech", "text": "Maybe you'll get to the stars -- some day! But right now, hadn't you better be getting to bed, son?"}, "text_section2": {"id": 2, "text_section_shape": {"bounding_box": {"coords": [[461, 42], [461, 82], [543, 82], [543, 42], [461, 42]], "pascal_voc_coords": [42, 461, 82, 543]}}, "speaker_referent": "X1", "type": "speech", "text": "Yes, Dad... I-I guess so --"}}, "setting": {"location_referent": "L2", "location_information_amount_ordinal": 5, "location_information_amount_binary": 1}}, "panel3": {"id": 3, "panel_shape": {"polygon": {"coords": [[50, 254], [312, 257], [312, 482], [42, 479], [50, 255], [50, 255]]}, "bounding_box": {"coords": [[48, 254], [48, 481], [311, 481], [311, 254], [48, 254]], "pascal_voc_coords": [254, 48, 481, 311]}}, "agents": {"agent1": {"id": 1, "agent_shape": {"polygon": {"coords": [[103, 353], [119, 347], [129, 347], [130, 346], [130, 333], [139, 318], [158, 311], [175, 316], [188, 325], [190, 340], [172, 369], [190, 377], [210, 377], [233, 382], [244, 388], [256, 406], [255, 416], [275, 428], [295, 432], [307, 432], [312, 430], [311, 462], [303, 465], [295, 462], [292, 454], [285, 451], [263, 445], [234, 436], [225, 433], [218, 438], [210, 437], [183, 446], [182, 453], [226, 447], [251, 445], [261, 449], [272, 461], [282, 470], [293, 481], [255, 478], [247, 471], [238, 471], [231, 474], [196, 472], [159, 470], [118, 472], [85, 474], [76, 459], [72, 441], [73, 414], [81, 386], [90, 367]]}}, "referent": "X1", "introduced_coreferent": "none", "animacy_type": "human"}}, "text_sections": {"text_section1": {"id": 1, "text_section_shape": {"bounding_box": {"coords": [[50, 255], [50, 298], [311, 298], [311, 255], [50, 255]], "pascal_voc_coords": [255, 50, 298, 311]}}, "speaker_referent": "N/A", "type": "third_person_narration", "text": "Your father understands... but even that doesn't help! He says good night and then you lie there with the yearning tearing you apart, until it's just too much to bear..."}, "text_section2": {"id": 2, "text_section_shape": {"bounding_box": {"coords": [[172, 300], [172, 360], [311, 360], [311, 300], [172, 300]], "pascal_voc_coords": [300, 172, 360, 311]}}, "speaker_referent": "X1", "type": "thought", "text": "I've got to get away from here! I've got to see those other worlds! I've got to!"}}, "setting": {"location_referent": "L4", "location_information_amount_ordinal": 3, "location_information_amount_binary": 1}}, "panel4": {"id": 4, "panel_shape": {"polygon": {"coords": [[325, 256], [606, 260], [603, 486], [322, 483], [324, 257], [324, 257]]}, "bounding_box": {"coords": [[324, 254], [324, 484], [604, 484], [604, 254], [324, 254]], "pascal_voc_coords": [254, 324, 484, 604]}}, "agents": {"agent1": {"id": 1, "agent_shape": {"polygon": {"coords": [[380, 348], [393, 343], [404, 340], [408, 333], [418, 333], [418, 341], [432, 345], [424, 349], [418, 347], [405, 353], [413, 356], [422, 350], [427, 354], [427, 359], [408, 363], [415, 372], [416, 388], [413, 393], [407, 382], [404, 372], [390, 364], [384, 364], [369, 374], [363, 373], [354, 365], [348, 364], [340, 368], [340, 364], [346, 353], [358, 359], [368, 363], [374, 357]]}}, "referent": "X1", "introduced_coreferent": "none", "animacy_type": "human"}}, "text_sections": {"text_section1": {"id": 1, "text_section_shape": {"bounding_box": {"coords": [[327, 256], [327, 297], [604, 297], [604, 256], [327, 256]], "pascal_voc_coords": [256, 327, 297, 604]}}, "speaker_referent": "N/A", "type": "third_person_narration", "text": "The rocket port is on the other side of the desert... it's a long way... a dangerous way, but you've waited too long to turn back now!"}}, "setting": {"location_referent": "L4", "location_information_amount_ordinal": 4, "location_information_amount_binary": 1}}, "panel5": {"id": 5, "panel_shape": {"polygon": {"coords": [[46, 488], [313, 493], [312, 575], [325, 579], [335, 584], [334, 592], [330, 594], [322, 600], [332, 604], [331, 613], [326, 616], [321, 619], [316, 630], [312, 633], [313, 724], [42, 721], [44, 489], [44, 489]]}, "bounding_box": {"coords": [[42, 487], [42, 722], [311, 722], [311, 487], [42, 487]], "pascal_voc_coords": [487, 42, 722, 311]}}, "agents": {"agent1": {"id": 1, "agent_shape": {"polygon": {"coords": [[200, 553], [200, 544], [218, 535], [217, 528], [220, 523], [230, 529], [228, 539], [238, 543], [249, 538], [255, 543], [250, 546], [248, 546], [238, 550], [232, 549], [230, 554], [214, 553]]}}, "referent": "X1", "introduced_coreferent": "none", "animacy_type": "human"}}, "text_sections": {}, "setting": {"location_referent": "L5", "location_information_amount_ordinal": 5, "location_information_amount_binary": 1}}, "panel6": {"id": 6, "panel_shape": {"polygon": {"coords": [[324, 492], [602, 496], [597, 728], [322, 725], [325, 618], [333, 608], [334, 604], [323, 600], [333, 592], [333, 582], [325, 578], [324, 579], [324, 493], [324, 493]]}, "bounding_box": {"coords": [[323, 492], [323, 725], [599, 725], [599, 492], [323, 492]], "pascal_voc_coords": [492, 323, 725, 599]}}, "agents": {"agent1": {"id": 1, "agent_shape": {"polygon": {"coords": [[351, 532], [358, 532], [360, 542], [353, 542]]}}, "referent": "X1", "introduced_coreferent": "none", "animacy_type": "human"}, "agent2": {"id": 2, "agent_shape": {"polygon": {"coords": [[452, 558], [468, 561], [479, 570], [479, 576], [474, 584], [478, 587], [495, 590], [508, 611], [515, 637], [518, 649], [518, 676], [485, 714], [483, 712], [485, 696], [489, 681], [472, 687], [455, 689], [444, 695], [447, 701], [445, 712], [447, 722], [447, 726], [419, 725], [420, 705], [420, 690], [435, 679], [464, 660], [479, 651], [476, 643], [469, 638], [457, 631], [438, 650], [418, 651], [398, 648], [390, 649], [382, 645], [381, 635], [391, 635], [387, 628], [395, 629], [401, 638], [429, 634], [439, 621], [446, 608], [454, 601], [449, 597], [439, 588], [428, 583], [416, 583], [409, 579], [416, 575], [409, 564], [418, 561], [428, 569], [432, 573], [447, 575], [446, 570]]}}, "referent": "X3", "introduced_coreferent": "none", "animacy_type": "human"}}, "text_sections": {"text_section1": {"id": 1, "text_section_shape": {"bounding_box": {"coords": [[403, 494], [403, 531], [474, 531], [474, 494], [403, 494]], "pascal_voc_coords": [494, 403, 531, 474]}}, "speaker_referent": "X3", "type": "speech", "text": "Joey! No!!"}}, "setting": {"location_referent": "L5", "location_information_amount_ordinal": 4, "location_information_amount_binary": 1}}}, "page3": {"panel1": {"id": 1, "panel_shape": {"polygon": {"coords": [[64, 30], [315, 32], [314, 252], [61, 253], [62, 29], [62, 29]]}, "bounding_box": {"coords": [[62, 30], [62, 252], [313, 252], [313, 30], [62, 30]], "pascal_voc_coords": [30, 62, 252, 313]}}, "agents": {"agent1": {"id": 1, "agent_shape": {"polygon": {"coords": [[222, 166], [230, 166], [230, 176], [222, 176]]}}, "referent": "X1", "introduced_coreferent": "none", "animacy_type": "human"}}, "text_sections": {"text_section1": {"id": 1, "text_section_shape": {"bounding_box": {"coords": [[65, 32], [65, 72], [313, 72], [313, 32], [65, 32]], "pascal_voc_coords": [32, 65, 72, 313]}}, "speaker_referent": "N/A", "type": "third_person_narration", "text": "Suddenly, you're free! You can almost touch the stars you're so hungry for! You stare ahead, eagerly --- and the miles whirl by..."}, "text_section2": {"id": 2, "text_section_shape": {"bounding_box": {"coords": [[64, 74], [64, 128], [186, 128], [186, 74], [64, 74]], "pascal_voc_coords": [74, 64, 128, 186]}}, "speaker_referent": "X1", "type": "thought", "text": "There it is... the rocket fort!! I'll get a job -- maybe as a cabin boy!"}}, "setting": {"location_referent": "L1", "location_information_amount_ordinal": 4, "location_information_amount_binary": 1}}, "panel2": {"id": 2, "panel_shape": {"polygon": {"coords": [[338, 30], [479, 29], [483, 33], [596, 33], [596, 253], [323, 253], [326, 55], [322, 46], [318, 37], [329, 32], [339, 31], [339, 31]]}, "bounding_box": {"coords": [[325, 28], [325, 252], [594, 252], [594, 28], [325, 28]], "pascal_voc_coords": [28, 325, 252, 594]}}, "agents": {"agent1": {"id": 1, "agent_shape": {"polygon": {"coords": [[447, 90], [454, 88], [462, 90], [477, 87], [486, 95], [498, 103], [503, 110], [503, 119], [501, 135], [512, 137], [526, 147], [520, 158], [514, 156], [515, 151], [502, 145], [493, 140], [490, 130], [488, 136], [501, 151], [501, 154], [501, 157], [479, 137], [490, 131], [482, 125], [487, 116], [478, 108], [473, 117], [456, 117], [451, 117], [445, 122], [435, 117], [443, 111], [456, 111], [462, 105], [461, 103], [452, 103]]}}, "referent": "X1", "introduced_coreferent": "none", "animacy_type": "human"}}, "text_sections": {"text_section1": {"id": 1, "text_section_shape": {"bounding_box": {"coords": [[322, 28], [322, 59], [473, 59], [473, 28], [322, 28]], "pascal_voc_coords": [28, 322, 59, 473]}}, "speaker_referent": "N/A", "type": "third_person_narration", "text": "... And then, suddenly -- the engine dies!!"}, "text_section2": {"id": 2, "text_section_shape": {"bounding_box": {"coords": [[512, 31], [512, 67], [589, 67], [589, 31], [512, 31]], "pascal_voc_coords": [31, 512, 67, 589]}}, "speaker_referent": "X1", "type": "thought", "text": "What..."}}, "setting": {"location_referent": "L1", "location_information_amount_ordinal": 3, "location_information_amount_binary": 1}}, "panel3": {"id": 3, "panel_shape": {"polygon": {"coords": [[63, 261], [315, 261], [316, 479], [61, 479], [63, 261], [63, 261]]}, "bounding_box": {"coords": [[61, 260], [61, 478], [313, 478], [313, 260], [61, 260]], "pascal_voc_coords": [260, 61, 478, 313]}}, "agents": {"agent1": {"id": 1, "agent_shape": {"polygon": {"coords": [[144, 363], [165, 358], [182, 356], [197, 353], [199, 359], [174, 365], [187, 370], [181, 378], [179, 386], [189, 390], [187, 407], [190, 419], [185, 417], [182, 407], [179, 386], [176, 394], [171, 394], [164, 387], [159, 384], [159, 377], [150, 377], [147, 376]]}}, "referent": "X1", "introduced_coreferent": "none", "animacy_type": "human"}, "agent2": {"id": 2, "agent_shape": {"polygon": {"coords": [[122, 299], [138, 285], [161, 282], [177, 273], [177, 280], [171, 290], [153, 290], [153, 299], [164, 297], [186, 304], [168, 304], [155, 310], [170, 315], [182, 318], [195, 330], [179, 328], [163, 325], [141, 327], [129, 323], [119, 327], [111, 327], [103, 339], [99, 336], [107, 321], [114, 317], [91, 321], [61, 316], [61, 311], [85, 317], [103, 314], [113, 310], [102, 309], [93, 303], [87, 302], [87, 295], [108, 305], [113, 305]]}}, "referent": "X4", "introduced_coreferent": "none", "animacy_type": "animallike"}}, "text_sections": {"text_section1": {"id": 1, "text_section_shape": {"bounding_box": {"coords": [[180, 262], [180, 305], [312, 305], [312, 262], [180, 262]], "pascal_voc_coords": [262, 180, 305, 312]}}, "speaker_referent": "X1", "type": "thought", "text": "Empty! The fuel tank is empty! I'll crash!!"}}, "setting": {"location_referent": "L1", "location_information_amount_ordinal": 4, "location_information_amount_binary": 1}}, "panel4": {"id": 4, "panel_shape": {"polygon": {"coords": [[325, 260], [596, 261], [594, 500], [325, 498], [324, 260], [324, 260]]}, "bounding_box": {"coords": [[324, 259], [324, 497], [594, 497], [594, 259], [324, 259]], "pascal_voc_coords": [259, 324, 497, 594]}}, "agents": {"agent1": {"id": 1, "agent_shape": {"polygon": {"coords": [[479, 363], [496, 369], [493, 383], [504, 392], [514, 416], [505, 441], [510, 453], [496, 452], [489, 473], [480, 472], [488, 449], [484, 431], [473, 456], [461, 481], [461, 491], [452, 488], [456, 463], [464, 440], [465, 424], [473, 409], [473, 401], [457, 415], [454, 424], [446, 426], [439, 420], [454, 414], [467, 391], [470, 381], [478, 377]]}}, "referent": "X1", "introduced_coreferent": "none", "animacy_type": "human"}, "agent2": {"id": 2, "agent_shape": {"polygon": {"coords": [[561, 428], [575, 428], [582, 441], [589, 446], [589, 466], [591, 470], [582, 471], [576, 465], [569, 470], [560, 470], [559, 464], [554, 464], [545, 459], [545, 448], [553, 441], [562, 440]]}}, "referent": "X5", "introduced_coreferent": "none", "animacy_type": "animallike"}, "agent3": {"id": 3, "agent_shape": {"polygon": {"coords": [[534, 480], [540, 469], [553, 464], [558, 472], [572, 472], [585, 472], [593, 478], [592, 496], [539, 497], [549, 490], [538, 488]]}}, "referent": "X6", "introduced_coreferent": "none", "animacy_type": "animallike"}}, "text_sections": {"text_section1": {"id": 1, "text_section_shape": {"bounding_box": {"coords": [[327, 261], [327, 313], [593, 313], [593, 261], [327, 261]], "pascal_voc_coords": [261, 327, 313, 593]}}, "speaker_referent": "N/A", "type": "third_person_narration", "text": "But you don't crash! The emergency stabilizer takes over... the platform rights itself... glides... and in a few seconds, there is a slight jar as you touch ground..."}, "text_section2": {"id": 2, "text_section_shape": {"bounding_box": {"coords": [[420, 314], [420, 358], [593, 358], [593, 314], [420, 314]], "pascal_voc_coords": [314, 420, 358, 593]}}, "speaker_referent": "X1", "type": "thought", "text": "I'm down --- but where? I'm still a long way from the rocket fort!"}}, "setting": {"location_referent": "L1", "location_information_amount_ordinal": 5, "location_information_amount_binary": 1}}, "panel5": {"id": 5, "panel_shape": {"polygon": {"coords": [[60, 486], [316, 489], [316, 533], [59, 533], [59, 486], [59, 486]]}, "bounding_box": {"coords": [[59, 486], [59, 530], [313, 530], [313, 486], [59, 486]], "pascal_voc_coords": [486, 59, 530, 313]}}, "agents": {}, "text_sections": {"text_section1": {"id": 1, "text_section_shape": {"bounding_box": {"coords": [[60, 489], [60, 531], [312, 531], [312, 489], [60, 489]], "pascal_voc_coords": [489, 60, 531, 312]}}, "speaker_referent": "N/A", "type": "third_person_narration", "text": "You're down, yes... but you're far from safe! You back away... slowly! You begin to walk -- and great danger stalks you silently!"}}, "setting": {"location_referent": "N/A", "location_information_amount_ordinal": 1, "location_information_amount_binary": 0}}, "panel6": {"id": 6, "panel_shape": {"polygon": {"coords": [[60, 537], [325, 535], [324, 506], [387, 506], [387, 714], [60, 713], [59, 537], [59, 537]]}, "bounding_box": {"coords": [[59, 506], [59, 714], [386, 714], [386, 506], [59, 506]], "pascal_voc_coords": [506, 59, 714, 386]}}, "agents": {"agent1": {"id": 1, "agent_shape": {"polygon": {"coords": [[145, 563], [167, 574], [177, 586], [181, 593], [188, 600], [196, 614], [212, 618], [222, 624], [232, 622], [241, 626], [254, 626], [265, 630], [274, 615], [272, 609], [252, 602], [215, 590], [181, 572], [216, 576], [253, 576], [284, 575], [300, 575], [300, 566], [310, 576], [321, 579], [320, 570], [323, 558], [327, 558], [327, 575], [333, 583], [343, 588], [352, 595], [353, 599], [348, 599], [339, 621], [337, 628], [329, 627], [325, 623], [322, 616], [320, 615], [318, 604], [316, 600], [310, 600], [304, 610], [303, 633], [293, 657], [284, 673], [268, 678], [267, 684], [255, 690], [274, 701], [288, 703], [301, 707], [314, 714], [252, 714], [238, 709], [222, 706], [215, 702], [211, 704], [200, 702], [209, 699], [206, 688], [200, 686], [191, 678], [188, 684], [194, 700], [199, 704], [180, 705], [186, 715], [168, 710], [158, 704], [153, 681], [153, 676], [148, 676], [149, 658], [143, 660], [136, 669], [128, 677], [135, 690], [116, 682], [110, 671], [116, 662], [111, 662], [106, 665], [108, 673], [109, 683], [121, 699], [138, 707], [105, 704], [98, 702], [91, 692], [81, 677], [72, 667], [72, 659], [77, 647], [89, 644], [104, 643], [118, 635], [118, 633], [114, 627], [105, 639], [97, 638], [92, 638], [85, 641], [74, 641], [61, 658], [61, 544], [71, 539], [172, 539], [194, 548], [209, 559], [183, 548], [157, 541], [143, 540], [115, 541], [95, 547], [80, 556], [70, 563], [63, 574], [63, 574], [62, 600], [72, 595], [85, 585], [98, 573], [117, 565], [134, 564]]}}, "referent": "X2", "introduced_coreferent": "none", "animacy_type": "animallike"}, "agent2": {"id": 2, "agent_shape": {"polygon": {"coords": [[327, 656], [333, 649], [338, 633], [345, 633], [345, 626], [353, 622], [362, 628], [377, 629], [384, 624], [382, 634], [363, 634], [358, 637], [362, 647], [378, 655], [384, 650], [383, 658], [378, 662], [358, 654], [354, 650], [348, 658], [367, 673], [361, 692], [356, 690], [356, 675], [341, 666], [339, 683], [329, 687], [323, 694], [313, 694], [322, 681], [330, 675], [330, 666]]}}, "referent": "X1", "introduced_coreferent": "none", "animacy_type": "human"}}, "text_sections": {}, "setting": {"location_referent": "L1", "location_information_amount_ordinal": 5, "location_information_amount_binary": 1}}, "panel7": {"id": 7, "panel_shape": {"polygon": {"coords": [[397, 506], [594, 507], [594, 717], [395, 715], [397, 508], [397, 508]]}, "bounding_box": {"coords": [[397, 506], [397, 714], [592, 714], [592, 506], [397, 506]], "pascal_voc_coords": [506, 397, 714, 592]}}, "agents": {"agent1": {"id": 1, "agent_shape": {"polygon": {"coords": [[461, 610], [472, 606], [482, 609], [489, 618], [497, 613], [504, 614], [525, 608], [533, 615], [527, 622], [529, 625], [520, 625], [528, 631], [535, 638], [540, 675], [560, 677], [574, 681], [579, 681], [584, 691], [577, 693], [571, 688], [559, 688], [547, 688], [537, 685], [529, 685], [524, 681], [519, 658], [516, 655], [499, 662], [496, 667], [500, 674], [500, 684], [503, 697], [492, 697], [490, 683], [483, 675], [475, 677], [463, 677], [460, 684], [449, 679], [453, 673], [451, 667], [454, 666], [465, 672], [481, 665], [480, 663], [488, 654], [487, 648], [484, 643], [485, 635], [477, 632], [470, 632], [465, 629], [463, 624]]}}, "referent": "X1", "introduced_coreferent": "none", "animacy_type": "human"}, "agent2": {"id": 2, "agent_shape": {"polygon": {"coords": [[469, 565], [464, 558], [464, 543], [470, 542], [478, 541], [491, 545], [498, 553], [522, 549], [539, 544], [550, 539], [550, 532], [545, 525], [533, 522], [543, 519], [549, 523], [551, 544], [532, 554], [544, 555], [557, 566], [550, 566], [540, 560], [535, 560], [535, 567], [494, 576], [496, 566], [493, 567], [490, 573], [472, 578], [487, 564], [488, 557], [483, 548], [478, 548], [477, 554]]}}, "referent": "X2", "introduced_coreferent": "none", "animacy_type": "animallike"}}, "text_sections": {"text_section1": {"id": 1, "text_section_shape": {"bounding_box": {"coords": [[411, 508], [411, 538], [534, 538], [534, 508], [411, 508]], "pascal_voc_coords": [508, 411, 538, 534]}}, "speaker_referent": "X1", "type": "thought", "text": "It-it's following me!"}}, "setting": {"location_referent": "L1", "location_information_amount_ordinal": 5, "location_information_amount_binary": 1}}}, "page4": {"panel1": {"id": 1, "panel_shape": {"polygon": {"coords": [[55, 29], [316, 29], [319, 33], [597, 34], [596, 254], [55, 250], [54, 28], [54, 28]]}, "bounding_box": {"coords": [[54, 30], [54, 250], [595, 250], [595, 30], [54, 30]], "pascal_voc_coords": [30, 54, 250, 595]}}, "agents": {"agent1": {"id": 1, "agent_shape": {"polygon": {"coords": [[91, 116], [108, 118], [117, 123], [130, 136], [134, 153], [158, 167], [156, 176], [149, 176], [149, 173], [129, 161], [122, 147], [109, 157], [120, 179], [108, 182], [105, 179], [110, 176], [99, 156], [113, 139], [108, 135], [105, 134], [105, 140], [95, 148], [90, 151], [79, 151], [79, 149], [90, 146], [93, 142], [84, 140], [84, 137], [95, 137], [96, 130], [89, 129]]}}, "referent": "X1", "introduced_coreferent": "none", "animacy_type": "human"}, "agent2": {"id": 2, "agent_shape": {"polygon": {"coords": [[409, 132], [425, 121], [436, 109], [453, 103], [460, 103], [486, 89], [518, 86], [558, 84], [584, 82], [592, 79], [592, 73], [584, 67], [561, 54], [520, 51], [491, 54], [458, 65], [439, 73], [424, 78], [403, 81], [437, 67], [462, 53], [491, 43], [520, 36], [555, 34], [580, 37], [594, 42], [596, 115], [583, 118], [572, 119], [574, 127], [580, 125], [589, 125], [595, 126], [595, 149], [590, 153], [587, 175], [585, 190], [578, 203], [573, 208], [547, 209], [548, 203], [562, 184], [564, 174], [554, 175], [548, 194], [535, 220], [522, 226], [511, 219], [520, 206], [523, 188], [524, 172], [522, 166], [512, 166], [518, 171], [522, 172], [516, 181], [509, 181], [497, 196], [485, 213], [468, 217], [452, 218], [450, 218], [438, 235], [423, 241], [404, 243], [386, 239], [407, 229], [421, 217], [427, 207], [410, 217], [390, 218], [379, 222], [362, 221], [355, 232], [340, 231], [328, 234], [317, 230], [337, 218], [342, 211], [336, 201], [333, 196], [320, 198], [315, 203], [311, 215], [307, 218], [304, 214], [293, 219], [281, 226], [274, 232], [274, 238], [252, 239], [242, 237], [225, 240], [205, 238], [202, 234], [231, 227], [270, 203], [270, 197], [253, 199], [231, 204], [217, 207], [202, 211], [202, 217], [197, 229], [189, 230], [174, 245], [161, 247], [152, 247], [148, 240], [154, 240], [154, 232], [152, 223], [146, 221], [137, 219], [130, 211], [127, 203], [130, 198], [147, 190], [145, 186], [147, 181], [157, 177], [170, 163], [203, 132], [219, 121], [229, 122], [241, 120], [251, 120], [259, 119], [266, 114], [274, 111], [281, 104], [281, 96], [287, 90], [287, 87], [324, 74], [379, 65], [344, 79], [303, 99], [279, 124], [268, 144], [266, 151], [267, 161], [283, 152], [312, 140], [338, 133], [350, 127], [372, 123], [386, 124], [394, 126], [399, 128]]}}, "referent": "X2", "introduced_coreferent": "none", "animacy_type": "animallike"}}, "text_sections": {"text_section1": {"id": 1, "text_section_shape": {"bounding_box": {"coords": [[55, 32], [55, 73], [313, 73], [313, 32], [55, 32]], "pascal_voc_coords": [32, 55, 73, 313]}}, "speaker_referent": "N/A", "type": "third_person_narration", "text": "Forgotten, then, are your dreams of other worlds! -- you stumble on -- the hours pass. Then, at last, you can go no further..."}, "text_section2": {"id": 2, "text_section_shape": {"bounding_box": {"coords": [[123, 74], [123, 118], [281, 118], [281, 74], [123, 74]], "pascal_voc_coords": [74, 123, 118, 281]}}, "speaker_referent": "X1", "type": "thought", "text": "There's a rumbling in my head! It's no use... I'm too tired to keep going!"}}, "setting": {"location_referent": "L1", "location_information_amount_ordinal": 5, "location_information_amount_binary": 1}}, "panel2": {"id": 2, "panel_shape": {"polygon": {"coords": [[56, 256], [313, 258], [312, 496], [54, 492], [55, 256], [55, 256]]}, "bounding_box": {"coords": [[54, 255], [54, 493], [310, 493], [310, 255], [54, 255]], "pascal_voc_coords": [255, 54, 493, 310]}}, "agents": {"agent1": {"id": 1, "agent_shape": {"polygon": {"coords": [[97, 380], [106, 382], [104, 392], [116, 408], [112, 408], [103, 401], [103, 407], [113, 421], [106, 437], [100, 434], [104, 424], [97, 416], [93, 423], [84, 424], [70, 437], [68, 431], [81, 418], [88, 415], [92, 406], [91, 399], [85, 402], [82, 409], [75, 410], [80, 397], [91, 391], [90, 389]]}}, "referent": "X1", "introduced_coreferent": "none", "animacy_type": "human"}, "agent2": {"id": 2, "agent_shape": {"polygon": {"coords": [[222, 419], [241, 412], [266, 408], [247, 421], [259, 419], [275, 426], [271, 437], [260, 437], [255, 442], [250, 437], [245, 443], [235, 447], [220, 447], [234, 439], [240, 435], [237, 432], [229, 434], [223, 437], [216, 437], [207, 433], [207, 429], [213, 428]]}}, "referent": "X2", "introduced_coreferent": "none", "animacy_type": "animallike"}}, "text_sections": {"text_section1": {"id": 1, "text_section_shape": {"bounding_box": {"coords": [[55, 257], [55, 307], [311, 307], [311, 257], [55, 257]], "pascal_voc_coords": [257, 55, 307, 311]}}, "speaker_referent": "N/A", "type": "third_person_narration", "text": "The eyes of the cat-thing blaze at you with merciless cruelty! You realize that it is a creature of the desert... belongs here... and it is you who are the intruder..."}}, "setting": {"location_referent": "L1", "location_information_amount_ordinal": 5, "location_information_amount_binary": 1}}, "panel3": {"id": 3, "panel_shape": {"polygon": {"coords": [[325, 258], [596, 260], [594, 478], [323, 476], [326, 259], [326, 259]]}, "bounding_box": {"coords": [[325, 258], [325, 476], [593, 476], [593, 258], [325, 258]], "pascal_voc_coords": [258, 325, 476, 593]}}, "agents": {"agent1": {"id": 1, "agent_shape": {"polygon": {"coords": [[425, 299], [442, 292], [454, 288], [487, 291], [511, 296], [537, 297], [549, 293], [552, 289], [558, 289], [549, 298], [533, 301], [515, 301], [499, 301], [485, 300], [477, 300], [473, 302], [476, 307], [482, 309], [486, 305], [504, 320], [495, 322], [488, 320], [478, 323], [478, 327], [472, 329], [468, 327], [462, 327], [458, 330], [466, 330], [462, 344], [463, 361], [456, 362], [450, 360], [445, 353], [445, 345], [438, 357], [437, 368], [427, 382], [432, 395], [423, 396], [412, 391], [397, 383], [394, 381], [382, 376], [385, 368], [381, 360], [377, 352], [372, 339], [368, 333], [366, 330], [361, 329], [361, 334], [362, 343], [360, 353], [355, 357], [344, 349], [340, 340], [332, 336], [329, 327], [326, 318], [326, 309], [326, 297], [333, 300], [330, 308], [331, 316], [338, 310], [338, 299], [342, 285], [357, 286], [361, 299], [365, 303], [374, 298], [379, 290], [379, 301], [369, 307], [380, 313], [389, 321], [395, 327], [404, 327], [409, 318], [413, 314], [418, 314], [419, 313]]}}, "referent": "X2", "introduced_coreferent": "none", "animacy_type": "animallike"}, "agent2": {"id": 2, "agent_shape": {"polygon": {"coords": [[396, 407], [427, 413], [443, 415], [455, 412], [469, 404], [474, 398], [481, 387], [470, 386], [466, 385], [456, 383], [455, 378], [455, 371], [467, 364], [478, 356], [489, 352], [499, 346], [497, 339], [509, 334], [513, 334], [513, 329], [515, 329], [520, 330], [522, 344], [531, 346], [537, 346], [533, 350], [523, 350], [513, 349], [498, 359], [496, 366], [517, 361], [530, 365], [537, 369], [538, 378], [542, 371], [541, 364], [546, 356], [556, 352], [567, 349], [578, 350], [587, 354], [593, 362], [593, 378], [589, 382], [587, 391], [580, 394], [573, 394], [583, 401], [584, 413], [582, 421], [573, 421], [560, 423], [545, 433], [529, 437], [510, 440], [487, 443], [475, 444], [466, 443], [460, 436], [445, 437], [427, 445], [414, 450], [398, 444], [385, 436], [375, 435], [366, 432], [363, 436], [357, 447], [346, 456], [341, 462], [338, 466], [332, 475], [325, 475], [325, 456], [332, 445], [335, 433], [353, 415], [357, 410], [370, 407], [380, 408], [384, 408]]}}, "referent": "X1", "introduced_coreferent": "none", "animacy_type": "human"}}, "text_sections": {"text_section1": {"id": 1, "text_section_shape": {"bounding_box": {"coords": [[327, 258], [327, 285], [594, 285], [594, 258], [327, 258]], "pascal_voc_coords": [258, 327, 285, 594]}}, "speaker_referent": "N/A", "type": "third_person_narration", "text": "... and, like the desert, it is about to close in on you..."}}, "setting": {"location_referent": "L1", "location_information_amount_ordinal": 3, "location_information_amount_binary": 1}}, "panel4": {"id": 4, "panel_shape": {"polygon": {"coords": [[54, 500], [312, 504], [312, 710], [52, 707], [54, 501], [54, 501]]}, "bounding_box": {"coords": [[53, 501], [53, 708], [310, 708], [310, 501], [53, 501]], "pascal_voc_coords": [501, 53, 708, 310]}}, "agents": {"agent1": {"id": 1, "agent_shape": {"polygon": {"coords": [[92, 626], [121, 626], [126, 625], [132, 625], [132, 619], [136, 614], [145, 616], [150, 622], [144, 631], [150, 637], [152, 656], [160, 653], [168, 654], [164, 661], [148, 667], [142, 666], [139, 648], [127, 653], [122, 656], [122, 663], [124, 677], [121, 693], [111, 694], [101, 701], [97, 701], [92, 701], [89, 705], [74, 706], [74, 703], [86, 693], [104, 684], [84, 689], [75, 685], [71, 687], [68, 695], [59, 694], [61, 678], [77, 677], [79, 673], [96, 672], [98, 662], [97, 656], [102, 644], [110, 636], [97, 636], [90, 641], [86, 646], [92, 655], [83, 655], [77, 647], [81, 638]]}}, "referent": "X3", "introduced_coreferent": "none", "animacy_type": "human"}, "agent2": {"id": 2, "agent_shape": {"polygon": {"coords": [[122, 547], [144, 547], [151, 539], [163, 539], [168, 533], [185, 533], [194, 527], [206, 523], [206, 516], [202, 514], [194, 512], [187, 512], [179, 512], [200, 506], [215, 506], [235, 512], [246, 520], [252, 529], [262, 542], [255, 543], [251, 547], [250, 556], [244, 552], [238, 544], [234, 539], [225, 533], [213, 533], [205, 537], [202, 538], [207, 546], [218, 554], [227, 554], [237, 556], [249, 558], [254, 565], [249, 571], [238, 570], [239, 564], [213, 565], [211, 562], [188, 565], [179, 567], [199, 570], [198, 576], [186, 577], [180, 573], [170, 572], [170, 580], [156, 579], [156, 574], [153, 571], [151, 575], [136, 579], [130, 592], [119, 585], [126, 579], [128, 571], [122, 572], [115, 570], [105, 584], [97, 586], [89, 578], [83, 580], [68, 586], [53, 587], [54, 549], [65, 541], [68, 545], [55, 557], [55, 582], [69, 577], [93, 559], [108, 552]]}}, "referent": "X2", "introduced_coreferent": "none", "animacy_type": "animallike"}, "agent3": {"id": 3, "agent_shape": {"polygon": {"coords": [[275, 592], [293, 592], [294, 610], [298, 610], [291, 623], [293, 626], [293, 645], [287, 643], [286, 631], [278, 624], [276, 627], [263, 636], [255, 634], [270, 622], [270, 613], [275, 607], [273, 605]]}}, "referent": "X1", "introduced_coreferent": "none", "animacy_type": "human"}}, "text_sections": {"text_section1": {"id": 1, "text_section_shape": {"bounding_box": {"coords": [[55, 502], [55, 519], [177, 519], [177, 502], [55, 502]], "pascal_voc_coords": [502, 55, 519, 177]}}, "speaker_referent": "N/A", "type": "third_person_narration", "text": "Then it strikes!"}}, "setting": {"location_referent": "L1", "location_information_amount_ordinal": 5, "location_information_amount_binary": 1}}, "panel5": {"id": 5, "panel_shape": {"polygon": {"coords": [[324, 484], [594, 487], [594, 711], [322, 710], [323, 485], [323, 485]]}, "bounding_box": {"coords": [[322, 483], [322, 709], [592, 709], [592, 483], [322, 483]], "pascal_voc_coords": [483, 322, 709, 592]}}, "agents": {"agent1": {"id": 1, "agent_shape": {"polygon": {"coords": [[346, 620], [367, 596], [372, 595], [370, 587], [377, 578], [390, 581], [395, 586], [387, 604], [396, 617], [402, 619], [416, 614], [420, 604], [429, 609], [409, 627], [402, 629], [389, 624], [389, 635], [404, 658], [408, 662], [404, 691], [403, 696], [415, 701], [410, 702], [392, 702], [394, 690], [389, 689], [393, 669], [383, 654], [374, 672], [364, 682], [364, 691], [354, 696], [354, 703], [360, 708], [342, 708], [341, 699], [343, 692], [341, 681], [361, 665], [366, 649], [366, 639], [360, 639], [354, 631]]}}, "referent": "X3", "introduced_coreferent": "none", "animacy_type": "human"}, "agent2": {"id": 2, "agent_shape": {"polygon": {"coords": [[464, 536], [479, 542], [498, 535], [509, 533], [525, 530], [514, 514], [541, 516], [553, 528], [554, 539], [562, 546], [555, 559], [545, 561], [535, 568], [530, 575], [539, 576], [564, 558], [570, 547], [580, 546], [590, 550], [588, 558], [579, 557], [575, 569], [567, 580], [560, 583], [544, 597], [526, 607], [535, 618], [531, 628], [520, 642], [529, 647], [545, 647], [557, 650], [555, 661], [540, 665], [526, 659], [506, 630], [485, 628], [461, 634], [441, 649], [448, 667], [436, 674], [424, 650], [418, 659], [402, 645], [411, 642], [391, 634], [390, 625], [404, 630], [414, 625], [432, 608], [422, 605], [415, 613], [404, 619], [398, 618], [387, 602], [395, 585], [385, 579], [380, 579], [375, 586], [373, 594], [367, 597], [358, 589], [350, 578], [349, 564], [340, 548], [333, 539], [323, 534], [323, 525], [340, 534], [359, 554], [366, 564], [374, 570], [395, 569], [414, 560], [428, 553], [443, 545], [447, 543]]}}, "referent": "X2", "introduced_coreferent": "none", "animacy_type": "animallike"}}, "text_sections": {"text_section1": {"id": 1, "text_section_shape": {"bounding_box": {"coords": [[325, 486], [325, 512], [592, 512], [592, 486], [325, 486]], "pascal_voc_coords": [486, 325, 512, 592]}}, "speaker_referent": "N/A", "type": "third_person_narration", "text": "But fortunately for you, it has waited too long!"}}, "setting": {"location_referent": "L1", "location_information_amount_ordinal": 2, "location_information_amount_binary": 1}}}, "page5": {"panel1": {"id": 1, "panel_shape": {"polygon": {"coords": [[53, 23], [310, 25], [312, 247], [52, 246], [54, 23], [54, 23]]}, "bounding_box": {"coords": [[52, 22], [52, 245], [311, 245], [311, 22], [52, 22]], "pascal_voc_coords": [22, 52, 245, 311]}}, "agents": {"agent1": {"id": 1, "agent_shape": {"polygon": {"coords": [[88, 197], [77, 200], [68, 198], [61, 196], [61, 193], [54, 193], [54, 176], [64, 173], [72, 169], [81, 171], [88, 162], [88, 152], [87, 143], [81, 143], [74, 141], [67, 144], [60, 155], [61, 161], [53, 173], [54, 136], [56, 130], [68, 123], [73, 116], [73, 110], [69, 110], [64, 112], [53, 120], [55, 101], [67, 96], [71, 89], [87, 90], [98, 88], [100, 85], [89, 85], [80, 80], [77, 72], [81, 67], [87, 62], [76, 59], [71, 54], [72, 49], [77, 49], [86, 54], [103, 52], [112, 52], [114, 56], [109, 65], [127, 58], [144, 51], [153, 47], [190, 47], [200, 50], [196, 59], [189, 64], [182, 64], [172, 65], [172, 73], [152, 86], [140, 90], [143, 94], [153, 94], [159, 90], [168, 94], [172, 79], [176, 83], [171, 100], [178, 108], [184, 113], [191, 113], [201, 117], [192, 127], [185, 130], [169, 129], [170, 122], [167, 118], [164, 117], [153, 133], [149, 139], [153, 145], [145, 150], [138, 160], [127, 168], [139, 168], [143, 161], [154, 155], [154, 168], [160, 171], [155, 183], [132, 184], [135, 171], [126, 169], [110, 183], [101, 191]]}}, "referent": "X2", "introduced_coreferent": "none", "animacy_type": "ambiguous"}, "agent2": {"id": 2, "agent_shape": {"polygon": {"coords": [[219, 150], [215, 175], [230, 182], [234, 178], [241, 184], [233, 191], [226, 189], [208, 183], [202, 172], [201, 163], [193, 169], [190, 174], [193, 179], [206, 189], [213, 202], [209, 212], [209, 217], [202, 226], [202, 229], [206, 229], [210, 235], [204, 238], [192, 240], [189, 236], [193, 226], [190, 224], [192, 212], [196, 209], [197, 200], [182, 192], [175, 187], [172, 189], [159, 206], [150, 223], [138, 227], [135, 234], [137, 238], [135, 240], [118, 241], [125, 230], [134, 209], [146, 199], [155, 183], [174, 152], [167, 151], [155, 156], [140, 168], [132, 168], [144, 151], [164, 140], [181, 137], [187, 134], [195, 137], [194, 132], [201, 125], [210, 124], [216, 129], [216, 135], [210, 143]]}}, "referent": "X3", "introduced_coreferent": "none", "animacy_type": "human"}, "agent3": {"id": 3, "agent_shape": {"polygon": {"coords": [[253, 95], [266, 95], [269, 103], [286, 110], [294, 130], [291, 147], [302, 146], [295, 154], [285, 158], [278, 154], [275, 162], [265, 160], [268, 152], [268, 144], [262, 149], [254, 145], [268, 125], [257, 116], [256, 118], [243, 134], [228, 137], [230, 128], [236, 128], [250, 111], [248, 108]]}}, "referent": "X1", "introduced_coreferent": "none", "animacy_type": "human"}}, "text_sections": {"text_section1": {"id": 1, "text_section_shape": {"bounding_box": {"coords": [[55, 24], [55, 46], [309, 46], [309, 24], [55, 24]], "pascal_voc_coords": [24, 55, 46, 309]}}, "speaker_referent": "N/A", "type": "third_person_narration", "text": "When you turn, you see the most welcome sight in the world!"}, "text_section2": {"id": 2, "text_section_shape": {"bounding_box": {"coords": [[186, 49], [186, 92], [309, 92], [309, 49], [186, 49]], "pascal_voc_coords": [49, 186, 92, 309]}}, "speaker_referent": "X1", "type": "thought", "text": "...Dad... Dad! I did hear a rumbling... Dad's half-track!"}}, "setting": {"location_referent": "L1", "location_information_amount_ordinal": 4, "location_information_amount_binary": 1}}, "panel2": {"id": 2, "panel_shape": {"polygon": {"coords": [[323, 23], [602, 22], [599, 248], [323, 246], [322, 22], [322, 22]]}, "bounding_box": {"coords": [[322, 22], [322, 245], [599, 245], [599, 22], [322, 22]], "pascal_voc_coords": [22, 322, 245, 599]}}, "agents": {"agent1": {"id": 1, "agent_shape": {"polygon": {"coords": [[416, 136], [420, 128], [419, 122], [427, 116], [435, 116], [443, 121], [444, 128], [434, 139], [440, 149], [445, 160], [467, 155], [463, 161], [440, 167], [433, 161], [431, 181], [422, 204], [414, 226], [413, 244], [400, 244], [405, 234], [404, 233], [395, 246], [384, 244], [396, 224], [409, 206], [414, 187], [412, 183], [410, 165], [411, 155], [412, 148]]}}, "referent": "X1", "introduced_coreferent": "none", "animacy_type": "human"}, "agent2": {"id": 2, "agent_shape": {"polygon": {"coords": [[441, 91], [451, 96], [455, 110], [472, 123], [474, 131], [468, 153], [466, 164], [466, 174], [470, 197], [469, 219], [474, 236], [474, 244], [458, 245], [450, 241], [450, 246], [435, 246], [431, 238], [429, 195], [434, 178], [434, 163], [415, 153], [416, 143], [433, 150], [438, 147], [436, 138], [443, 128], [443, 119], [433, 115], [428, 107], [428, 100]]}}, "referent": "X3", "introduced_coreferent": "none", "animacy_type": "human"}}, "text_sections": {"text_section1": {"id": 1, "text_section_shape": {"bounding_box": {"coords": [[324, 23], [324, 57], [599, 57], [599, 23], [324, 23]], "pascal_voc_coords": [23, 324, 57, 599]}}, "speaker_referent": "N/A", "type": "third_person_narration", "text": "When your father takes you in his arms, you cling to him, and he holds you until your trembling ceases..."}, "text_section2": {"id": 2, "text_section_shape": {"bounding_box": {"coords": [[326, 59], [326, 97], [407, 97], [407, 59], [326, 59]], "pascal_voc_coords": [59, 326, 97, 407]}}, "speaker_referent": "X1", "type": "speech", "text": "But how -- how did you find me?"}, "text_section3": {"id": 3, "text_section_shape": {"bounding_box": {"coords": [[444, 59], [444, 158], [599, 158], [599, 59], [444, 59]], "pascal_voc_coords": [59, 444, 158, 599]}}, "speaker_referent": "X3", "type": "speech", "text": "I saw you leave, Joey! It wasn't hard to guess where you were headed! -- I followed you and found the platform, so I looked for your trail!"}}, "setting": {"location_referent": "L1", "location_information_amount_ordinal": 4, "location_information_amount_binary": 1}}, "panel3": {"id": 3, "panel_shape": {"polygon": {"coords": [[52, 255], [341, 256], [342, 480], [50, 479], [52, 255], [52, 255]]}, "bounding_box": {"coords": [[52, 255], [52, 480], [340, 480], [340, 255], [52, 255]], "pascal_voc_coords": [255, 52, 480, 340]}}, "agents": {"agent1": {"id": 1, "agent_shape": {"polygon": {"coords": [[265, 359], [274, 350], [275, 338], [287, 338], [287, 351], [293, 364], [306, 363], [302, 368], [292, 370], [292, 386], [292, 405], [291, 414], [298, 421], [292, 424], [286, 422], [285, 432], [275, 428], [276, 418], [274, 413], [275, 391], [269, 376], [269, 372]]}}, "referent": "X3", "introduced_coreferent": "none", "animacy_type": "human"}, "agent2": {"id": 2, "agent_shape": {"polygon": {"coords": [[306, 346], [320, 347], [320, 359], [327, 365], [326, 384], [320, 398], [323, 428], [317, 424], [309, 418], [307, 393], [304, 382], [304, 371], [307, 361]]}}, "referent": "X1", "introduced_coreferent": "none", "animacy_type": "human"}}, "text_sections": {"text_section1": {"id": 1, "text_section_shape": {"bounding_box": {"coords": [[210, 256], [210, 338], [339, 338], [339, 256], [210, 256]], "pascal_voc_coords": [256, 210, 338, 339]}}, "speaker_referent": "X3", "type": "speech", "text": "You were heading for the rocket port, weren't you? For the stars... but they will still be there.. when you grow up, Joey!"}}, "setting": {"location_referent": "L1", "location_information_amount_ordinal": 5, "location_information_amount_binary": 1}}, "panel4": {"id": 4, "panel_shape": {"polygon": {"coords": [[352, 256], [601, 256], [599, 480], [352, 479], [351, 257], [351, 257]]}, "bounding_box": {"coords": [[351, 255], [351, 479], [598, 479], [598, 255], [351, 255]], "pascal_voc_coords": [255, 351, 479, 598]}}, "agents": {"agent1": {"id": 1, "agent_shape": {"polygon": {"coords": [[368, 334], [386, 330], [403, 336], [409, 351], [408, 362], [408, 371], [401, 379], [399, 388], [411, 393], [416, 402], [412, 413], [408, 422], [408, 433], [352, 438], [353, 382], [360, 380], [362, 373], [356, 366], [357, 358], [361, 352], [361, 348]]}}, "referent": "X1", "introduced_coreferent": "none", "animacy_type": "human"}, "agent2": {"id": 2, "agent_shape": {"polygon": {"coords": [[448, 307], [469, 304], [480, 308], [492, 321], [486, 329], [487, 343], [479, 356], [482, 369], [514, 378], [521, 391], [522, 374], [531, 364], [548, 366], [558, 370], [555, 378], [554, 392], [553, 395], [584, 396], [593, 382], [587, 373], [598, 362], [596, 397], [553, 397], [541, 402], [535, 407], [541, 417], [546, 420], [552, 421], [552, 423], [535, 423], [527, 422], [515, 425], [478, 428], [474, 435], [468, 437], [442, 430], [419, 434], [413, 421], [413, 416], [418, 404], [414, 394], [406, 390], [416, 379], [433, 370], [447, 362], [445, 353], [440, 344], [435, 337], [435, 323], [440, 318]]}}, "referent": "X3", "introduced_coreferent": "none", "animacy_type": "human"}}, "text_sections": {"text_section1": {"id": 1, "text_section_shape": {"bounding_box": {"coords": [[354, 257], [354, 288], [431, 288], [431, 257], [354, 257]], "pascal_voc_coords": [257, 354, 288, 431]}}, "speaker_referent": "X1", "type": "speech", "text": "Dad, I-I'm sorry --"}, "text_section2": {"id": 2, "text_section_shape": {"bounding_box": {"coords": [[422, 258], [422, 323], [596, 323], [596, 258], [422, 258]], "pascal_voc_coords": [258, 422, 323, 596]}}, "speaker_referent": "X3", "type": "speech", "text": "It's all right, Joey. You made a mistake. Now, you know. You're not ready! But like I said, you'll make it... some day!"}}, "setting": {"location_referent": "L6", "location_information_amount_ordinal": 3, "location_information_amount_binary": 1}}, "panel5": {"id": 5, "panel_shape": {"polygon": {"coords": [[49, 488], [312, 488], [313, 718], [49, 715], [49, 488], [49, 488]]}, "bounding_box": {"coords": [[48, 487], [48, 715], [313, 715], [313, 487], [48, 487]], "pascal_voc_coords": [487, 48, 715, 313]}}, "agents": {"agent1": {"id": 1, "agent_shape": {"polygon": {"coords": [[62, 584], [79, 577], [91, 576], [98, 578], [103, 596], [105, 615], [98, 618], [98, 634], [104, 640], [111, 655], [114, 669], [115, 686], [132, 695], [158, 699], [167, 695], [177, 691], [192, 692], [192, 695], [170, 710], [163, 713], [64, 712], [61, 696], [64, 667], [69, 639], [72, 629], [70, 624], [63, 620], [57, 606], [53, 597]]}}, "referent": "X1", "introduced_coreferent": "none", "animacy_type": "human"}}, "text_sections": {"text_section1": {"id": 1, "text_section_shape": {"bounding_box": {"coords": [[51, 489], [51, 528], [311, 528], [311, 489], [51, 489]], "pascal_voc_coords": [489, 51, 528, 311]}}, "speaker_referent": "N/A", "type": "third_person_narration", "text": "So your father takes you home... you stare up at the Earth, yearning... and you hardly notice Deimos and Phobos, the two martian moons!"}}, "setting": {"location_referent": "L7", "location_information_amount_ordinal": 3, "location_information_amount_binary": 1}}, "panel6": {"id": 6, "panel_shape": {"polygon": {"coords": [[325, 489], [598, 490], [596, 721], [325, 717], [324, 489], [324, 489]]}, "bounding_box": {"coords": [[324, 488], [324, 717], [595, 717], [595, 488], [324, 488]], "pascal_voc_coords": [488, 324, 717, 595]}}, "agents": {"agent1": {"id": 1, "agent_shape": {"polygon": {"coords": [[427, 592], [439, 593], [444, 601], [452, 605], [456, 616], [456, 628], [459, 632], [449, 651], [446, 665], [471, 679], [479, 684], [480, 693], [480, 719], [372, 715], [374, 677], [378, 673], [401, 664], [414, 655], [414, 650], [410, 637], [407, 625], [409, 612], [414, 603], [417, 599]]}}, "referent": "X1", "introduced_coreferent": "none", "animacy_type": "human"}}, "text_sections": {"text_section1": {"id": 1, "text_section_shape": {"bounding_box": {"coords": [[327, 490], [327, 538], [595, 538], [595, 490], [327, 490]], "pascal_voc_coords": [490, 327, 538, 595]}}, "speaker_referent": "N/A", "type": "third_person_narration", "text": "After all you were born on Mars -- its moons and the planet, Earth, above, are old stuff to you! What you're interested in is the universe beyond!"}, "text_section2": {"id": 2, "text_section_shape": {"bounding_box": {"coords": [[542, 686], [542, 717], [590, 717], [590, 686], [542, 686]], "pascal_voc_coords": [686, 542, 717, 590]}}, "speaker_referent": "N/A", "type": "third_person_narration", "text": "The End."}}, "setting": {"location_referent": "L7", "location_information_amount_ordinal": 3, "location_information_amount_binary": 1}}}}